{
    "pools":  [
                  {
                      "entries":  [
                                      {
                                          "name":  "candycraftmod:suguard_sentry_key_hole",
                                          "type":  "minecraft:item"
                                      }
                                  ],
                      "rolls":  1,
                      "conditions":  [
                                         {
                                             "condition":  "minecraft:survives_explosion"
                                         }
                                     ]
                  }
              ],
    "type":  "minecraft:block"
}
